PyMSQ/__init__.py
PyMSQ/msq.py
PyMSQ/data/chr.txt
PyMSQ/data/effects.txt
PyMSQ/data/group.txt
PyMSQ/data/pedigree.txt
PyMSQ/data/phase.txt
pymsq-0.1.1.dist-info/METADATA
pymsq-0.1.1.dist-info/WHEEL
pymsq-0.1.1.dist-info/top_level.txt
pymsq-0.1.1.dist-info/RECORD
