Metadata-Version: 2.4
Name: PyMSQ
Version: 0.1.1
Summary: A Python package for estimating Mendelian sampling-related quantities
Home-page: https://github.com/aromemusa/PyMSQ
Download-URL: https://github.com/aromemusa/PyMSQ/dist/PyMSQ-0.1.1.tar.gz
Author: Abdulraheem Musa, Norbert Reinsch
Author-email: musa@fbn-dummerstorf.de, reinsch@fbn-dummerstorf.de
License: MIT
Keywords: Mendelian sampling,variance,covariance,similarity,selection,haplotype diversity
Classifier: Development Status :: 4 - Beta
Classifier: Intended Audience :: Science/Research
Classifier: License :: OSI Approved :: MIT License
Classifier: Programming Language :: Python :: 3.8
Classifier: Programming Language :: Python :: 3.9
Classifier: Programming Language :: Python :: 3.10
Classifier: Programming Language :: Python :: 3.11
Requires-Python: >=3.8
Requires-Dist: numpy<1.25
Requires-Dist: pandas
Requires-Dist: scipy
Requires-Dist: numba<0.58
Dynamic: author
Dynamic: author-email
Dynamic: classifier
Dynamic: description
Dynamic: description-content-type
Dynamic: download-url
Dynamic: home-page
Dynamic: keywords
Dynamic: license
Dynamic: requires-dist
Dynamic: requires-python
Dynamic: summary
